flet_gradient_borders/__init__.py
flet_gradient_borders-1.0.0.dist-info/METADATA
flet_gradient_borders-1.0.0.dist-info/WHEEL
flet_gradient_borders-1.0.0.dist-info/top_level.txt
flet_gradient_borders-1.0.0.dist-info/RECORD
