Metadata-Version: 2.4
Name: flet_gradient_borders
Version: 1.0.0
Summary: A flet component for gradient borders
Author-email: Benit Mulindwa <mulindwabenit@gmail.com>
License: MIT
Project-URL: Homepage, https://github.com/Benitmulindwa/flet_gradient_borders
Classifier: Programming Language :: Python :: 3
Classifier: License :: OSI Approved :: MIT License
Classifier: Operating System :: OS Independent
Requires-Python: >=3.8
Requires-Dist: flet
